db_connect/__init__.py
db_connect/mongo_crud.py
db_connect/sql_crud.py
danny_db_connect-0.0.2.dist-info/LICENSE
danny_db_connect-0.0.2.dist-info/METADATA
danny_db_connect-0.0.2.dist-info/WHEEL
danny_db_connect-0.0.2.dist-info/top_level.txt
danny_db_connect-0.0.2.dist-info/RECORD
