Metadata-Version: 2.1
Name: danny_db_connect
Version: 0.0.2
Summary: A python package for connecting with MySQL and MongoDB.
Home-page: https://github.com/dannychemm123/db_connector
Author: dannychemm123
Author-email: dannychemm121@gmail.com
License: MIT
Project-URL: Bug Tracker, https://github.com/dannychemm123/db_connector/issues
Classifier: Programming Language :: Python :: 3.8
Classifier: Operating System :: OS Independent
Requires-Python: >=3.7
License-File: LICENSE
Requires-Dist: pymongo
Requires-Dist: mysql-connector-python
Requires-Dist: pymongo[srv]
Requires-Dist: dnspython
Requires-Dist: pandas
Requires-Dist: numpy
Requires-Dist: ensure
Requires-Dist: pytest
Provides-Extra: testing
Requires-Dist: pytest >=7.1.3 ; extra == 'testing'
Requires-Dist: mypy >=0.971 ; extra == 'testing'
Requires-Dist: flake8 >=5.0.4 ; extra == 'testing'
Requires-Dist: tox >=3.25.1 ; extra == 'testing'
Requires-Dist: black >=22.8.0 ; extra == 'testing'
